lsfm_destripe/__init__.py
lsfm_destripe/constant.py
lsfm_destripe/core.py
lsfm_destripe/guided_filter_upsample.py
lsfm_destripe/loss_term_jax.py
lsfm_destripe/loss_term_torch.py
lsfm_destripe/network_jax.py
lsfm_destripe/network_torch.py
lsfm_destripe/utils.py
lsfm_destripe/utils_jax.py
lsfm_destripe/utils_torch.py
lsfm_destripe/bin/__init__.py
lsfm_destripe/bin/run_destripe.py
lsfm_destripe-0.2.0.dist-info/LICENSE
lsfm_destripe-0.2.0.dist-info/METADATA
lsfm_destripe-0.2.0.dist-info/WHEEL
lsfm_destripe-0.2.0.dist-info/entry_points.txt
lsfm_destripe-0.2.0.dist-info/top_level.txt
lsfm_destripe-0.2.0.dist-info/RECORD
